app/__init__.py
app/app.py
app/builder.py
app/components.py
app/console.py
app/file_utils.py
app/visitors.py
structorex-0.1.1.dist-info/METADATA
structorex-0.1.1.dist-info/WHEEL
structorex-0.1.1.dist-info/entry_points.txt
structorex-0.1.1.dist-info/top_level.txt
structorex-0.1.1.dist-info/RECORD
